{
  "symbol": "BOME/USDT:USDT",
  "side": "short",
  "entryPrice": 0.0006112,
  "leverage": 8,
  "riskLevel": "LOW",
  "confidence": 68,
  "atr": 6.571428571428421e-7,
  "atrPct": 0.0010751682872101474,
  "atrSlMult": 1.5,
  "channel": {
    "width": 0.000003300000000000026,
    "widthPct": 0.005399214659685906,
    "midpoint": 0.00061035,
    "upperLine": {
      "point1": {
        "index": 171,
        "price": 0.0006134,
        "type": "HIGH",
        "timestamp": 1779404760000,
        "confirmed": true
      },
      "point2": {
        "index": 198,
        "price": 0.000612,
        "type": "HIGH",
        "timestamp": 1779406380000,
        "confirmed": true
      }
    },
    "lowerLine": {
      "point1": {
        "index": 166,
        "price": 0.00061,
        "type": "LOW",
        "timestamp": 1779404460000,
        "confirmed": true
      },
      "point2": {
        "index": 180,
        "price": 0.0006087,
        "type": "LOW",
        "timestamp": 1779405300000,
        "confirmed": true
      }
    }
  },
  "riskReward": {
    "rr": 0.4924242424242382,
    "pass": true
  },
  "zone": {
    "zone": "OB",
    "inZone": true,
    "depthPct": 0.5151515151515231
  },
  "trends": {
    "macro": "SIDEWAYS_EXPANDING",
    "structural": "BEARISH",
    "trading": "BEARISH"
  },
  "momentum": {
    "rangeMomentum": true,
    "slopeMomentumPass": true,
    "slopeMomentumRatio": 1
  },
  "exitTargets": {
    "sl": 0.0006121857142857142,
    "targets": [
      {
        "price": 0.0006095499999999999,
        "percentage": 75
      },
      {
        "price": 0.000608725,
        "percentage": 25
      }
    ]
  },
  "candles": {
    "1m": [
      {
        "time": 1779400500,
        "open": 0.000615,
        "high": 0.0006151,
        "low": 0.000615,
        "close": 0.000615
      },
      {
        "time": 1779400560,
        "open": 0.000615,
        "high": 0.0006151,
        "low": 0.0006143,
        "close": 0.0006146
      },
      {
        "time": 1779400620,
        "open": 0.0006146,
        "high": 0.0006147,
        "low": 0.0006143,
        "close": 0.0006144
      },
      {
        "time": 1779400680,
        "open": 0.0006143,
        "high": 0.0006152,
        "low": 0.000614,
        "close": 0.0006152
      },
      {
        "time": 1779400740,
        "open": 0.0006152,
        "high": 0.0006153,
        "low": 0.0006146,
        "close": 0.0006153
      },
      {
        "time": 1779400800,
        "open": 0.0006154,
        "high": 0.000616,
        "low": 0.0006145,
        "close": 0.0006145
      },
      {
        "time": 1779400860,
        "open": 0.0006146,
        "high": 0.0006152,
        "low": 0.0006146,
        "close": 0.000615
      },
      {
        "time": 1779400920,
        "open": 0.0006149,
        "high": 0.0006167,
        "low": 0.0006148,
        "close": 0.0006166
      },
      {
        "time": 1779400980,
        "open": 0.0006169,
        "high": 0.0006183,
        "low": 0.0006165,
        "close": 0.0006179
      },
      {
        "time": 1779401040,
        "open": 0.000618,
        "high": 0.0006186,
        "low": 0.0006178,
        "close": 0.0006184
      },
      {
        "time": 1779401100,
        "open": 0.0006183,
        "high": 0.000619,
        "low": 0.0006183,
        "close": 0.0006185
      },
      {
        "time": 1779401160,
        "open": 0.0006184,
        "high": 0.0006184,
        "low": 0.0006174,
        "close": 0.0006181
      },
      {
        "time": 1779401220,
        "open": 0.0006179,
        "high": 0.000618,
        "low": 0.0006175,
        "close": 0.000618
      },
      {
        "time": 1779401280,
        "open": 0.000618,
        "high": 0.0006182,
        "low": 0.0006179,
        "close": 0.0006181
      },
      {
        "time": 1779401340,
        "open": 0.0006182,
        "high": 0.0006182,
        "low": 0.0006179,
        "close": 0.0006182
      },
      {
        "time": 1779401400,
        "open": 0.0006186,
        "high": 0.0006195,
        "low": 0.0006181,
        "close": 0.0006182
      },
      {
        "time": 1779401460,
        "open": 0.000618,
        "high": 0.0006181,
        "low": 0.0006172,
        "close": 0.0006172
      },
      {
        "time": 1779401520,
        "open": 0.0006173,
        "high": 0.0006173,
        "low": 0.0006167,
        "close": 0.0006167
      },
      {
        "time": 1779401580,
        "open": 0.0006166,
        "high": 0.000617,
        "low": 0.0006158,
        "close": 0.0006164
      },
      {
        "time": 1779401640,
        "open": 0.0006164,
        "high": 0.0006164,
        "low": 0.000616,
        "close": 0.0006161
      },
      {
        "time": 1779401700,
        "open": 0.0006161,
        "high": 0.000617,
        "low": 0.000616,
        "close": 0.000617
      },
      {
        "time": 1779401760,
        "open": 0.0006169,
        "high": 0.000617,
        "low": 0.0006152,
        "close": 0.0006158
      },
      {
        "time": 1779401820,
        "open": 0.0006158,
        "high": 0.0006167,
        "low": 0.0006158,
        "close": 0.0006166
      },
      {
        "time": 1779401880,
        "open": 0.0006165,
        "high": 0.0006173,
        "low": 0.0006164,
        "close": 0.0006173
      },
      {
        "time": 1779401940,
        "open": 0.0006173,
        "high": 0.0006173,
        "low": 0.0006169,
        "close": 0.0006173
      },
      {
        "time": 1779402000,
        "open": 0.0006171,
        "high": 0.0006171,
        "low": 0.0006156,
        "close": 0.0006156
      },
      {
        "time": 1779402060,
        "open": 0.0006156,
        "high": 0.000616,
        "low": 0.0006156,
        "close": 0.0006159
      },
      {
        "time": 1779402120,
        "open": 0.0006159,
        "high": 0.0006159,
        "low": 0.0006151,
        "close": 0.0006151
      },
      {
        "time": 1779402180,
        "open": 0.000615,
        "high": 0.0006151,
        "low": 0.000615,
        "close": 0.000615
      },
      {
        "time": 1779402240,
        "open": 0.0006151,
        "high": 0.0006156,
        "low": 0.0006147,
        "close": 0.0006156
      },
      {
        "time": 1779402300,
        "open": 0.0006154,
        "high": 0.0006157,
        "low": 0.0006153,
        "close": 0.0006155
      },
      {
        "time": 1779402360,
        "open": 0.0006154,
        "high": 0.000616,
        "low": 0.0006154,
        "close": 0.000616
      },
      {
        "time": 1779402420,
        "open": 0.000616,
        "high": 0.000616,
        "low": 0.0006152,
        "close": 0.0006152
      },
      {
        "time": 1779402480,
        "open": 0.0006152,
        "high": 0.0006155,
        "low": 0.000615,
        "close": 0.0006151
      },
      {
        "time": 1779402540,
        "open": 0.0006152,
        "high": 0.0006153,
        "low": 0.0006152,
        "close": 0.0006153
      },
      {
        "time": 1779402600,
        "open": 0.0006154,
        "high": 0.0006158,
        "low": 0.0006148,
        "close": 0.0006158
      },
      {
        "time": 1779402660,
        "open": 0.0006155,
        "high": 0.0006161,
        "low": 0.0006155,
        "close": 0.0006161
      },
      {
        "time": 1779402720,
        "open": 0.0006161,
        "high": 0.0006162,
        "low": 0.0006151,
        "close": 0.0006151
      },
      {
        "time": 1779402780,
        "open": 0.0006151,
        "high": 0.0006152,
        "low": 0.0006145,
        "close": 0.0006145
      },
      {
        "time": 1779402840,
        "open": 0.0006145,
        "high": 0.0006145,
        "low": 0.0006135,
        "close": 0.0006135
      },
      {
        "time": 1779402900,
        "open": 0.0006135,
        "high": 0.0006135,
        "low": 0.000613,
        "close": 0.0006134
      },
      {
        "time": 1779402960,
        "open": 0.0006133,
        "high": 0.0006133,
        "low": 0.0006129,
        "close": 0.0006133
      },
      {
        "time": 1779403020,
        "open": 0.0006133,
        "high": 0.0006133,
        "low": 0.0006122,
        "close": 0.0006123
      },
      {
        "time": 1779403080,
        "open": 0.0006123,
        "high": 0.0006125,
        "low": 0.000612,
        "close": 0.0006124
      },
      {
        "time": 1779403140,
        "open": 0.0006123,
        "high": 0.0006123,
        "low": 0.000611,
        "close": 0.000611
      },
      {
        "time": 1779403200,
        "open": 0.0006109,
        "high": 0.0006119,
        "low": 0.0006109,
        "close": 0.0006119
      },
      {
        "time": 1779403260,
        "open": 0.0006115,
        "high": 0.0006123,
        "low": 0.0006115,
        "close": 0.0006121
      },
      {
        "time": 1779403320,
        "open": 0.000612,
        "high": 0.0006122,
        "low": 0.0006118,
        "close": 0.0006122
      },
      {
        "time": 1779403380,
        "open": 0.0006121,
        "high": 0.0006121,
        "low": 0.0006114,
        "close": 0.0006116
      },
      {
        "time": 1779403440,
        "open": 0.0006117,
        "high": 0.0006119,
        "low": 0.0006113,
        "close": 0.0006115
      },
      {
        "time": 1779403500,
        "open": 0.0006116,
        "high": 0.0006122,
        "low": 0.0006112,
        "close": 0.0006122
      },
      {
        "time": 1779403560,
        "open": 0.0006124,
        "high": 0.0006131,
        "low": 0.0006121,
        "close": 0.0006125
      },
      {
        "time": 1779403620,
        "open": 0.0006125,
        "high": 0.0006127,
        "low": 0.0006124,
        "close": 0.0006126
      },
      {
        "time": 1779403680,
        "open": 0.0006119,
        "high": 0.0006127,
        "low": 0.0006119,
        "close": 0.0006127
      },
      {
        "time": 1779403740,
        "open": 0.0006126,
        "high": 0.0006126,
        "low": 0.0006123,
        "close": 0.0006123
      },
      {
        "time": 1779403800,
        "open": 0.0006122,
        "high": 0.0006122,
        "low": 0.0006113,
        "close": 0.0006115
      },
      {
        "time": 1779403860,
        "open": 0.0006115,
        "high": 0.0006116,
        "low": 0.0006113,
        "close": 0.0006115
      },
      {
        "time": 1779403920,
        "open": 0.0006115,
        "high": 0.0006115,
        "low": 0.000611,
        "close": 0.0006114
      },
      {
        "time": 1779403980,
        "open": 0.0006115,
        "high": 0.0006121,
        "low": 0.0006115,
        "close": 0.0006121
      },
      {
        "time": 1779404040,
        "open": 0.0006121,
        "high": 0.0006122,
        "low": 0.0006119,
        "close": 0.0006121
      },
      {
        "time": 1779404100,
        "open": 0.000612,
        "high": 0.000612,
        "low": 0.0006115,
        "close": 0.0006115
      },
      {
        "time": 1779404160,
        "open": 0.0006116,
        "high": 0.0006116,
        "low": 0.0006109,
        "close": 0.0006114
      },
      {
        "time": 1779404220,
        "open": 0.0006113,
        "high": 0.0006114,
        "low": 0.0006112,
        "close": 0.0006112
      },
      {
        "time": 1779404280,
        "open": 0.0006111,
        "high": 0.0006114,
        "low": 0.000611,
        "close": 0.000611
      },
      {
        "time": 1779404340,
        "open": 0.000611,
        "high": 0.000612,
        "low": 0.0006109,
        "close": 0.000612
      },
      {
        "time": 1779404400,
        "open": 0.0006119,
        "high": 0.000612,
        "low": 0.0006115,
        "close": 0.0006118
      },
      {
        "time": 1779404460,
        "open": 0.0006118,
        "high": 0.0006118,
        "low": 0.00061,
        "close": 0.0006107
      },
      {
        "time": 1779404520,
        "open": 0.0006105,
        "high": 0.0006107,
        "low": 0.0006103,
        "close": 0.0006107
      },
      {
        "time": 1779404580,
        "open": 0.0006108,
        "high": 0.0006124,
        "low": 0.0006108,
        "close": 0.0006124
      },
      {
        "time": 1779404640,
        "open": 0.0006125,
        "high": 0.0006125,
        "low": 0.0006115,
        "close": 0.0006118
      },
      {
        "time": 1779404700,
        "open": 0.0006118,
        "high": 0.0006119,
        "low": 0.0006114,
        "close": 0.0006119
      },
      {
        "time": 1779404760,
        "open": 0.0006119,
        "high": 0.0006134,
        "low": 0.0006119,
        "close": 0.0006133
      },
      {
        "time": 1779404820,
        "open": 0.0006132,
        "high": 0.0006132,
        "low": 0.0006128,
        "close": 0.000613
      },
      {
        "time": 1779404880,
        "open": 0.000613,
        "high": 0.0006134,
        "low": 0.000613,
        "close": 0.0006133
      },
      {
        "time": 1779404940,
        "open": 0.0006133,
        "high": 0.0006138,
        "low": 0.0006132,
        "close": 0.0006132
      },
      {
        "time": 1779405000,
        "open": 0.0006131,
        "high": 0.0006131,
        "low": 0.0006125,
        "close": 0.0006125
      },
      {
        "time": 1779405060,
        "open": 0.0006126,
        "high": 0.0006131,
        "low": 0.0006123,
        "close": 0.0006123
      },
      {
        "time": 1779405120,
        "open": 0.0006123,
        "high": 0.0006123,
        "low": 0.0006116,
        "close": 0.0006116
      },
      {
        "time": 1779405180,
        "open": 0.0006113,
        "high": 0.0006115,
        "low": 0.000611,
        "close": 0.0006114
      },
      {
        "time": 1779405240,
        "open": 0.0006113,
        "high": 0.0006113,
        "low": 0.0006098,
        "close": 0.0006098
      },
      {
        "time": 1779405300,
        "open": 0.0006097,
        "high": 0.0006099,
        "low": 0.0006087,
        "close": 0.0006099
      },
      {
        "time": 1779405360,
        "open": 0.0006098,
        "high": 0.0006105,
        "low": 0.0006098,
        "close": 0.0006103
      },
      {
        "time": 1779405420,
        "open": 0.0006104,
        "high": 0.0006104,
        "low": 0.0006099,
        "close": 0.0006104
      },
      {
        "time": 1779405480,
        "open": 0.0006104,
        "high": 0.0006104,
        "low": 0.0006098,
        "close": 0.0006099
      },
      {
        "time": 1779405540,
        "open": 0.0006099,
        "high": 0.0006103,
        "low": 0.0006096,
        "close": 0.0006103
      },
      {
        "time": 1779405600,
        "open": 0.0006103,
        "high": 0.0006104,
        "low": 0.0006101,
        "close": 0.0006102
      },
      {
        "time": 1779405660,
        "open": 0.0006101,
        "high": 0.0006101,
        "low": 0.0006093,
        "close": 0.0006096
      },
      {
        "time": 1779405720,
        "open": 0.0006096,
        "high": 0.0006098,
        "low": 0.0006095,
        "close": 0.0006097
      },
      {
        "time": 1779405780,
        "open": 0.0006097,
        "high": 0.0006099,
        "low": 0.0006097,
        "close": 0.0006097
      },
      {
        "time": 1779405840,
        "open": 0.0006098,
        "high": 0.0006107,
        "low": 0.0006096,
        "close": 0.0006107
      },
      {
        "time": 1779405900,
        "open": 0.0006108,
        "high": 0.0006111,
        "low": 0.0006103,
        "close": 0.000611
      },
      {
        "time": 1779405960,
        "open": 0.0006111,
        "high": 0.0006114,
        "low": 0.0006111,
        "close": 0.0006113
      },
      {
        "time": 1779406020,
        "open": 0.0006114,
        "high": 0.0006115,
        "low": 0.0006106,
        "close": 0.0006107
      },
      {
        "time": 1779406080,
        "open": 0.0006106,
        "high": 0.000611,
        "low": 0.0006106,
        "close": 0.000611
      },
      {
        "time": 1779406140,
        "open": 0.0006108,
        "high": 0.0006111,
        "low": 0.0006107,
        "close": 0.0006109
      },
      {
        "time": 1779406200,
        "open": 0.0006108,
        "high": 0.000611,
        "low": 0.0006097,
        "close": 0.0006097
      },
      {
        "time": 1779406260,
        "open": 0.00061,
        "high": 0.0006105,
        "low": 0.0006097,
        "close": 0.0006104
      },
      {
        "time": 1779406320,
        "open": 0.0006105,
        "high": 0.0006113,
        "low": 0.0006105,
        "close": 0.0006113
      },
      {
        "time": 1779406380,
        "open": 0.0006115,
        "high": 0.000612,
        "low": 0.0006113,
        "close": 0.0006113
      },
      {
        "time": 1779406440,
        "open": 0.0006113,
        "high": 0.0006113,
        "low": 0.0006112,
        "close": 0.0006112
      }
    ],
    "3m": [
      {
        "time": 1779388560,
        "open": 0.0006146,
        "high": 0.0006162,
        "low": 0.0006141,
        "close": 0.0006162
      },
      {
        "time": 1779388740,
        "open": 0.0006162,
        "high": 0.0006166,
        "low": 0.0006151,
        "close": 0.0006159
      },
      {
        "time": 1779388920,
        "open": 0.0006161,
        "high": 0.0006169,
        "low": 0.0006157,
        "close": 0.0006159
      },
      {
        "time": 1779389100,
        "open": 0.0006159,
        "high": 0.0006163,
        "low": 0.0006141,
        "close": 0.0006151
      },
      {
        "time": 1779389280,
        "open": 0.000615,
        "high": 0.000615,
        "low": 0.0006103,
        "close": 0.0006115
      },
      {
        "time": 1779389460,
        "open": 0.0006114,
        "high": 0.0006129,
        "low": 0.0006082,
        "close": 0.0006095
      },
      {
        "time": 1779389640,
        "open": 0.0006095,
        "high": 0.0006105,
        "low": 0.0006066,
        "close": 0.0006089
      },
      {
        "time": 1779389820,
        "open": 0.0006088,
        "high": 0.0006121,
        "low": 0.0006087,
        "close": 0.000612
      },
      {
        "time": 1779390000,
        "open": 0.000612,
        "high": 0.0006139,
        "low": 0.0006114,
        "close": 0.0006119
      },
      {
        "time": 1779390180,
        "open": 0.000612,
        "high": 0.000613,
        "low": 0.0006115,
        "close": 0.000612
      },
      {
        "time": 1779390360,
        "open": 0.000612,
        "high": 0.0006133,
        "low": 0.0006105,
        "close": 0.0006129
      },
      {
        "time": 1779390540,
        "open": 0.000613,
        "high": 0.0006142,
        "low": 0.0006127,
        "close": 0.0006129
      },
      {
        "time": 1779390720,
        "open": 0.0006128,
        "high": 0.0006137,
        "low": 0.0006125,
        "close": 0.0006137
      },
      {
        "time": 1779390900,
        "open": 0.0006137,
        "high": 0.0006144,
        "low": 0.0006125,
        "close": 0.0006144
      },
      {
        "time": 1779391080,
        "open": 0.0006144,
        "high": 0.0006148,
        "low": 0.0006136,
        "close": 0.0006136
      },
      {
        "time": 1779391260,
        "open": 0.0006136,
        "high": 0.000614,
        "low": 0.000613,
        "close": 0.0006137
      },
      {
        "time": 1779391440,
        "open": 0.0006137,
        "high": 0.0006141,
        "low": 0.0006124,
        "close": 0.0006132
      },
      {
        "time": 1779391620,
        "open": 0.0006132,
        "high": 0.000614,
        "low": 0.0006115,
        "close": 0.000612
      },
      {
        "time": 1779391800,
        "open": 0.000612,
        "high": 0.0006131,
        "low": 0.000612,
        "close": 0.0006128
      },
      {
        "time": 1779391980,
        "open": 0.0006128,
        "high": 0.0006138,
        "low": 0.0006119,
        "close": 0.0006138
      },
      {
        "time": 1779392160,
        "open": 0.0006138,
        "high": 0.0006141,
        "low": 0.0006125,
        "close": 0.0006127
      },
      {
        "time": 1779392340,
        "open": 0.0006127,
        "high": 0.0006127,
        "low": 0.0006117,
        "close": 0.0006123
      },
      {
        "time": 1779392520,
        "open": 0.0006122,
        "high": 0.0006132,
        "low": 0.0006118,
        "close": 0.0006129
      },
      {
        "time": 1779392700,
        "open": 0.0006128,
        "high": 0.000613,
        "low": 0.0006123,
        "close": 0.000613
      },
      {
        "time": 1779392880,
        "open": 0.000613,
        "high": 0.0006152,
        "low": 0.0006128,
        "close": 0.0006147
      },
      {
        "time": 1779393060,
        "open": 0.0006149,
        "high": 0.000616,
        "low": 0.0006145,
        "close": 0.0006148
      },
      {
        "time": 1779393240,
        "open": 0.0006148,
        "high": 0.000617,
        "low": 0.0006135,
        "close": 0.0006164
      },
      {
        "time": 1779393420,
        "open": 0.0006166,
        "high": 0.0006169,
        "low": 0.0006155,
        "close": 0.0006157
      },
      {
        "time": 1779393600,
        "open": 0.0006151,
        "high": 0.0006158,
        "low": 0.0006145,
        "close": 0.0006145
      },
      {
        "time": 1779393780,
        "open": 0.0006146,
        "high": 0.0006154,
        "low": 0.000614,
        "close": 0.0006153
      },
      {
        "time": 1779393960,
        "open": 0.0006154,
        "high": 0.0006162,
        "low": 0.0006153,
        "close": 0.0006155
      },
      {
        "time": 1779394140,
        "open": 0.0006156,
        "high": 0.000616,
        "low": 0.0006143,
        "close": 0.0006144
      },
      {
        "time": 1779394320,
        "open": 0.0006144,
        "high": 0.0006149,
        "low": 0.0006143,
        "close": 0.0006144
      },
      {
        "time": 1779394500,
        "open": 0.0006145,
        "high": 0.0006147,
        "low": 0.0006129,
        "close": 0.0006129
      },
      {
        "time": 1779394680,
        "open": 0.0006128,
        "high": 0.0006133,
        "low": 0.0006126,
        "close": 0.0006126
      },
      {
        "time": 1779394860,
        "open": 0.0006126,
        "high": 0.0006139,
        "low": 0.0006126,
        "close": 0.0006136
      },
      {
        "time": 1779395040,
        "open": 0.0006136,
        "high": 0.0006145,
        "low": 0.0006133,
        "close": 0.0006133
      },
      {
        "time": 1779395220,
        "open": 0.0006132,
        "high": 0.0006133,
        "low": 0.0006123,
        "close": 0.0006131
      },
      {
        "time": 1779395400,
        "open": 0.0006131,
        "high": 0.000614,
        "low": 0.0006128,
        "close": 0.000614
      },
      {
        "time": 1779395580,
        "open": 0.0006141,
        "high": 0.0006143,
        "low": 0.000613,
        "close": 0.0006133
      },
      {
        "time": 1779395760,
        "open": 0.0006134,
        "high": 0.0006141,
        "low": 0.0006128,
        "close": 0.0006128
      },
      {
        "time": 1779395940,
        "open": 0.0006128,
        "high": 0.0006138,
        "low": 0.0006128,
        "close": 0.0006137
      },
      {
        "time": 1779396120,
        "open": 0.0006137,
        "high": 0.0006146,
        "low": 0.0006135,
        "close": 0.0006146
      },
      {
        "time": 1779396300,
        "open": 0.0006149,
        "high": 0.0006153,
        "low": 0.0006142,
        "close": 0.0006153
      },
      {
        "time": 1779396480,
        "open": 0.0006153,
        "high": 0.0006165,
        "low": 0.0006146,
        "close": 0.000615
      },
      {
        "time": 1779396660,
        "open": 0.0006153,
        "high": 0.0006153,
        "low": 0.0006123,
        "close": 0.0006126
      },
      {
        "time": 1779396840,
        "open": 0.0006126,
        "high": 0.0006132,
        "low": 0.0006122,
        "close": 0.0006124
      },
      {
        "time": 1779397020,
        "open": 0.0006124,
        "high": 0.0006127,
        "low": 0.0006118,
        "close": 0.0006126
      },
      {
        "time": 1779397200,
        "open": 0.0006127,
        "high": 0.0006143,
        "low": 0.0006127,
        "close": 0.0006132
      },
      {
        "time": 1779397380,
        "open": 0.0006132,
        "high": 0.0006136,
        "low": 0.0006129,
        "close": 0.0006136
      },
      {
        "time": 1779397560,
        "open": 0.0006137,
        "high": 0.0006148,
        "low": 0.0006136,
        "close": 0.0006145
      },
      {
        "time": 1779397740,
        "open": 0.0006145,
        "high": 0.0006153,
        "low": 0.0006145,
        "close": 0.0006151
      },
      {
        "time": 1779397920,
        "open": 0.0006151,
        "high": 0.0006151,
        "low": 0.0006135,
        "close": 0.0006142
      },
      {
        "time": 1779398100,
        "open": 0.0006142,
        "high": 0.0006151,
        "low": 0.0006142,
        "close": 0.0006151
      },
      {
        "time": 1779398280,
        "open": 0.0006151,
        "high": 0.0006157,
        "low": 0.0006147,
        "close": 0.0006153
      },
      {
        "time": 1779398460,
        "open": 0.0006152,
        "high": 0.0006157,
        "low": 0.0006149,
        "close": 0.0006156
      },
      {
        "time": 1779398640,
        "open": 0.0006155,
        "high": 0.0006173,
        "low": 0.0006154,
        "close": 0.0006168
      },
      {
        "time": 1779398820,
        "open": 0.0006167,
        "high": 0.0006172,
        "low": 0.0006163,
        "close": 0.0006171
      },
      {
        "time": 1779399000,
        "open": 0.0006172,
        "high": 0.0006176,
        "low": 0.0006162,
        "close": 0.0006162
      },
      {
        "time": 1779399180,
        "open": 0.0006162,
        "high": 0.0006178,
        "low": 0.0006162,
        "close": 0.0006175
      },
      {
        "time": 1779399360,
        "open": 0.0006175,
        "high": 0.0006177,
        "low": 0.0006172,
        "close": 0.0006172
      },
      {
        "time": 1779399540,
        "open": 0.0006172,
        "high": 0.0006173,
        "low": 0.0006149,
        "close": 0.000615
      },
      {
        "time": 1779399720,
        "open": 0.000615,
        "high": 0.0006152,
        "low": 0.0006146,
        "close": 0.000615
      },
      {
        "time": 1779399900,
        "open": 0.000615,
        "high": 0.0006151,
        "low": 0.0006149,
        "close": 0.0006149
      },
      {
        "time": 1779400080,
        "open": 0.000615,
        "high": 0.000615,
        "low": 0.0006143,
        "close": 0.0006146
      },
      {
        "time": 1779400260,
        "open": 0.0006147,
        "high": 0.0006157,
        "low": 0.0006147,
        "close": 0.0006153
      },
      {
        "time": 1779400440,
        "open": 0.0006152,
        "high": 0.0006153,
        "low": 0.0006143,
        "close": 0.0006146
      },
      {
        "time": 1779400620,
        "open": 0.0006146,
        "high": 0.0006153,
        "low": 0.000614,
        "close": 0.0006153
      },
      {
        "time": 1779400800,
        "open": 0.0006154,
        "high": 0.0006167,
        "low": 0.0006145,
        "close": 0.0006166
      },
      {
        "time": 1779400980,
        "open": 0.0006169,
        "high": 0.000619,
        "low": 0.0006165,
        "close": 0.0006185
      },
      {
        "time": 1779401160,
        "open": 0.0006184,
        "high": 0.0006184,
        "low": 0.0006174,
        "close": 0.0006181
      },
      {
        "time": 1779401340,
        "open": 0.0006182,
        "high": 0.0006195,
        "low": 0.0006172,
        "close": 0.0006172
      },
      {
        "time": 1779401520,
        "open": 0.0006173,
        "high": 0.0006173,
        "low": 0.0006158,
        "close": 0.0006161
      },
      {
        "time": 1779401700,
        "open": 0.0006161,
        "high": 0.000617,
        "low": 0.0006152,
        "close": 0.0006166
      },
      {
        "time": 1779401880,
        "open": 0.0006165,
        "high": 0.0006173,
        "low": 0.0006156,
        "close": 0.0006156
      },
      {
        "time": 1779402060,
        "open": 0.0006156,
        "high": 0.000616,
        "low": 0.000615,
        "close": 0.000615
      },
      {
        "time": 1779402240,
        "open": 0.0006151,
        "high": 0.000616,
        "low": 0.0006147,
        "close": 0.000616
      },
      {
        "time": 1779402420,
        "open": 0.000616,
        "high": 0.000616,
        "low": 0.000615,
        "close": 0.0006153
      },
      {
        "time": 1779402600,
        "open": 0.0006154,
        "high": 0.0006162,
        "low": 0.0006148,
        "close": 0.0006151
      },
      {
        "time": 1779402780,
        "open": 0.0006151,
        "high": 0.0006152,
        "low": 0.000613,
        "close": 0.0006134
      },
      {
        "time": 1779402960,
        "open": 0.0006133,
        "high": 0.0006133,
        "low": 0.000612,
        "close": 0.0006124
      },
      {
        "time": 1779403140,
        "open": 0.0006123,
        "high": 0.0006123,
        "low": 0.0006109,
        "close": 0.0006121
      },
      {
        "time": 1779403320,
        "open": 0.000612,
        "high": 0.0006122,
        "low": 0.0006113,
        "close": 0.0006115
      },
      {
        "time": 1779403500,
        "open": 0.0006116,
        "high": 0.0006131,
        "low": 0.0006112,
        "close": 0.0006126
      },
      {
        "time": 1779403680,
        "open": 0.0006119,
        "high": 0.0006127,
        "low": 0.0006113,
        "close": 0.0006115
      },
      {
        "time": 1779403860,
        "open": 0.0006115,
        "high": 0.0006121,
        "low": 0.000611,
        "close": 0.0006121
      },
      {
        "time": 1779404040,
        "open": 0.0006121,
        "high": 0.0006122,
        "low": 0.0006109,
        "close": 0.0006114
      },
      {
        "time": 1779404220,
        "open": 0.0006113,
        "high": 0.000612,
        "low": 0.0006109,
        "close": 0.000612
      },
      {
        "time": 1779404400,
        "open": 0.0006119,
        "high": 0.000612,
        "low": 0.00061,
        "close": 0.0006107
      },
      {
        "time": 1779404580,
        "open": 0.0006108,
        "high": 0.0006125,
        "low": 0.0006108,
        "close": 0.0006119
      },
      {
        "time": 1779404760,
        "open": 0.0006119,
        "high": 0.0006134,
        "low": 0.0006119,
        "close": 0.0006133
      },
      {
        "time": 1779404940,
        "open": 0.0006133,
        "high": 0.0006138,
        "low": 0.0006123,
        "close": 0.0006123
      },
      {
        "time": 1779405120,
        "open": 0.0006123,
        "high": 0.0006123,
        "low": 0.0006098,
        "close": 0.0006098
      },
      {
        "time": 1779405300,
        "open": 0.0006097,
        "high": 0.0006105,
        "low": 0.0006087,
        "close": 0.0006104
      },
      {
        "time": 1779405480,
        "open": 0.0006104,
        "high": 0.0006104,
        "low": 0.0006096,
        "close": 0.0006102
      },
      {
        "time": 1779405660,
        "open": 0.0006101,
        "high": 0.0006101,
        "low": 0.0006093,
        "close": 0.0006097
      },
      {
        "time": 1779405840,
        "open": 0.0006098,
        "high": 0.0006114,
        "low": 0.0006096,
        "close": 0.0006113
      },
      {
        "time": 1779406020,
        "open": 0.0006114,
        "high": 0.0006115,
        "low": 0.0006106,
        "close": 0.0006109
      },
      {
        "time": 1779406200,
        "open": 0.0006108,
        "high": 0.0006113,
        "low": 0.0006097,
        "close": 0.0006113
      },
      {
        "time": 1779406380,
        "open": 0.0006115,
        "high": 0.000612,
        "low": 0.0006112,
        "close": 0.0006112
      }
    ],
    "15m": [
      {
        "time": 1779317100,
        "open": 0.0006217,
        "high": 0.000624,
        "low": 0.000621,
        "close": 0.0006214
      },
      {
        "time": 1779318000,
        "open": 0.0006213,
        "high": 0.0006233,
        "low": 0.0006196,
        "close": 0.0006201
      },
      {
        "time": 1779318900,
        "open": 0.00062,
        "high": 0.0006219,
        "low": 0.0006189,
        "close": 0.0006203
      },
      {
        "time": 1779319800,
        "open": 0.0006203,
        "high": 0.0006238,
        "low": 0.0006191,
        "close": 0.000623
      },
      {
        "time": 1779320700,
        "open": 0.000623,
        "high": 0.0006266,
        "low": 0.0006229,
        "close": 0.0006263
      },
      {
        "time": 1779321600,
        "open": 0.0006263,
        "high": 0.000629,
        "low": 0.0006251,
        "close": 0.0006275
      },
      {
        "time": 1779322500,
        "open": 0.0006275,
        "high": 0.0006355,
        "low": 0.0006274,
        "close": 0.0006355
      },
      {
        "time": 1779323400,
        "open": 0.0006356,
        "high": 0.0006408,
        "low": 0.0006342,
        "close": 0.0006407
      },
      {
        "time": 1779324300,
        "open": 0.0006406,
        "high": 0.000642,
        "low": 0.0006365,
        "close": 0.000638
      },
      {
        "time": 1779325200,
        "open": 0.0006382,
        "high": 0.0006455,
        "low": 0.0006378,
        "close": 0.000644
      },
      {
        "time": 1779326100,
        "open": 0.0006441,
        "high": 0.0006456,
        "low": 0.0006344,
        "close": 0.0006368
      },
      {
        "time": 1779327000,
        "open": 0.0006368,
        "high": 0.0006393,
        "low": 0.0006335,
        "close": 0.0006336
      },
      {
        "time": 1779327900,
        "open": 0.0006337,
        "high": 0.0006364,
        "low": 0.0006315,
        "close": 0.0006364
      },
      {
        "time": 1779328800,
        "open": 0.0006364,
        "high": 0.0006367,
        "low": 0.0006312,
        "close": 0.0006352
      },
      {
        "time": 1779329700,
        "open": 0.0006354,
        "high": 0.000638,
        "low": 0.0006342,
        "close": 0.0006344
      },
      {
        "time": 1779330600,
        "open": 0.0006343,
        "high": 0.0006369,
        "low": 0.0006332,
        "close": 0.0006359
      },
      {
        "time": 1779331500,
        "open": 0.0006358,
        "high": 0.0006358,
        "low": 0.000631,
        "close": 0.0006313
      },
      {
        "time": 1779332400,
        "open": 0.0006312,
        "high": 0.0006348,
        "low": 0.0006308,
        "close": 0.0006336
      },
      {
        "time": 1779333300,
        "open": 0.0006337,
        "high": 0.0006366,
        "low": 0.000633,
        "close": 0.0006354
      },
      {
        "time": 1779334200,
        "open": 0.0006355,
        "high": 0.0006359,
        "low": 0.0006309,
        "close": 0.000632
      },
      {
        "time": 1779335100,
        "open": 0.000632,
        "high": 0.0006341,
        "low": 0.0006296,
        "close": 0.000633
      },
      {
        "time": 1779336000,
        "open": 0.000633,
        "high": 0.0006347,
        "low": 0.0006299,
        "close": 0.00063
      },
      {
        "time": 1779336900,
        "open": 0.0006301,
        "high": 0.000633,
        "low": 0.0006296,
        "close": 0.000632
      },
      {
        "time": 1779337800,
        "open": 0.0006321,
        "high": 0.0006333,
        "low": 0.0006283,
        "close": 0.0006303
      },
      {
        "time": 1779338700,
        "open": 0.0006303,
        "high": 0.0006306,
        "low": 0.0006287,
        "close": 0.0006287
      },
      {
        "time": 1779339600,
        "open": 0.0006287,
        "high": 0.0006296,
        "low": 0.000627,
        "close": 0.0006292
      },
      {
        "time": 1779340500,
        "open": 0.0006292,
        "high": 0.0006303,
        "low": 0.0006269,
        "close": 0.0006275
      },
      {
        "time": 1779341400,
        "open": 0.0006275,
        "high": 0.0006275,
        "low": 0.0006238,
        "close": 0.0006253
      },
      {
        "time": 1779342300,
        "open": 0.0006252,
        "high": 0.0006269,
        "low": 0.0006215,
        "close": 0.0006215
      },
      {
        "time": 1779343200,
        "open": 0.0006215,
        "high": 0.0006224,
        "low": 0.0006191,
        "close": 0.0006209
      },
      {
        "time": 1779344100,
        "open": 0.0006208,
        "high": 0.000623,
        "low": 0.0006195,
        "close": 0.0006219
      },
      {
        "time": 1779345000,
        "open": 0.0006219,
        "high": 0.0006226,
        "low": 0.000616,
        "close": 0.0006164
      },
      {
        "time": 1779345900,
        "open": 0.0006165,
        "high": 0.0006168,
        "low": 0.0006141,
        "close": 0.0006152
      },
      {
        "time": 1779346800,
        "open": 0.0006153,
        "high": 0.0006161,
        "low": 0.0006107,
        "close": 0.0006131
      },
      {
        "time": 1779347700,
        "open": 0.000613,
        "high": 0.0006138,
        "low": 0.0006112,
        "close": 0.0006125
      },
      {
        "time": 1779348600,
        "open": 0.0006124,
        "high": 0.0006154,
        "low": 0.000612,
        "close": 0.0006147
      },
      {
        "time": 1779349500,
        "open": 0.0006147,
        "high": 0.0006177,
        "low": 0.0006146,
        "close": 0.0006153
      },
      {
        "time": 1779350400,
        "open": 0.0006153,
        "high": 0.0006202,
        "low": 0.0006142,
        "close": 0.0006201
      },
      {
        "time": 1779351300,
        "open": 0.0006201,
        "high": 0.0006206,
        "low": 0.0006151,
        "close": 0.0006189
      },
      {
        "time": 1779352200,
        "open": 0.0006188,
        "high": 0.0006189,
        "low": 0.0006129,
        "close": 0.0006147
      },
      {
        "time": 1779353100,
        "open": 0.0006148,
        "high": 0.0006151,
        "low": 0.000612,
        "close": 0.0006133
      },
      {
        "time": 1779354000,
        "open": 0.0006132,
        "high": 0.0006154,
        "low": 0.0006124,
        "close": 0.0006133
      },
      {
        "time": 1779354900,
        "open": 0.0006132,
        "high": 0.0006139,
        "low": 0.000611,
        "close": 0.0006117
      },
      {
        "time": 1779355800,
        "open": 0.0006118,
        "high": 0.0006121,
        "low": 0.0006055,
        "close": 0.0006069
      },
      {
        "time": 1779356700,
        "open": 0.0006069,
        "high": 0.0006089,
        "low": 0.000605,
        "close": 0.0006056
      },
      {
        "time": 1779357600,
        "open": 0.0006056,
        "high": 0.0006069,
        "low": 0.0006035,
        "close": 0.0006053
      },
      {
        "time": 1779358500,
        "open": 0.0006053,
        "high": 0.0006073,
        "low": 0.0005958,
        "close": 0.0005985
      },
      {
        "time": 1779359400,
        "open": 0.0005984,
        "high": 0.0005998,
        "low": 0.0005939,
        "close": 0.0005991
      },
      {
        "time": 1779360300,
        "open": 0.0005991,
        "high": 0.0005991,
        "low": 0.0005944,
        "close": 0.0005975
      },
      {
        "time": 1779361200,
        "open": 0.0005975,
        "high": 0.0006008,
        "low": 0.0005953,
        "close": 0.0006001
      },
      {
        "time": 1779362100,
        "open": 0.0006001,
        "high": 0.0006011,
        "low": 0.000598,
        "close": 0.0005983
      },
      {
        "time": 1779363000,
        "open": 0.0005984,
        "high": 0.0006005,
        "low": 0.0005974,
        "close": 0.0005994
      },
      {
        "time": 1779363900,
        "open": 0.0005994,
        "high": 0.0006001,
        "low": 0.0005982,
        "close": 0.0005985
      },
      {
        "time": 1779364800,
        "open": 0.0005986,
        "high": 0.0006004,
        "low": 0.0005966,
        "close": 0.0005973
      },
      {
        "time": 1779365700,
        "open": 0.0005972,
        "high": 0.0005988,
        "low": 0.0005955,
        "close": 0.0005965
      },
      {
        "time": 1779366600,
        "open": 0.0005964,
        "high": 0.0006011,
        "low": 0.0005944,
        "close": 0.0005994
      },
      {
        "time": 1779367500,
        "open": 0.0005993,
        "high": 0.0006006,
        "low": 0.0005983,
        "close": 0.0005989
      },
      {
        "time": 1779368400,
        "open": 0.0005988,
        "high": 0.0006009,
        "low": 0.0005983,
        "close": 0.0005994
      },
      {
        "time": 1779369300,
        "open": 0.0005993,
        "high": 0.0006001,
        "low": 0.0005964,
        "close": 0.0005998
      },
      {
        "time": 1779370200,
        "open": 0.0005998,
        "high": 0.0005998,
        "low": 0.0005883,
        "close": 0.0005893
      },
      {
        "time": 1779371100,
        "open": 0.0005896,
        "high": 0.0005969,
        "low": 0.0005891,
        "close": 0.0005966
      },
      {
        "time": 1779372000,
        "open": 0.0005964,
        "high": 0.0005991,
        "low": 0.0005947,
        "close": 0.0005959
      },
      {
        "time": 1779372900,
        "open": 0.0005959,
        "high": 0.0005964,
        "low": 0.000592,
        "close": 0.0005962
      },
      {
        "time": 1779373800,
        "open": 0.0005963,
        "high": 0.0006021,
        "low": 0.0005963,
        "close": 0.0006003
      },
      {
        "time": 1779374700,
        "open": 0.0006003,
        "high": 0.0006012,
        "low": 0.0005977,
        "close": 0.0005992
      },
      {
        "time": 1779375600,
        "open": 0.0005994,
        "high": 0.0006066,
        "low": 0.000597,
        "close": 0.0006033
      },
      {
        "time": 1779376500,
        "open": 0.0006033,
        "high": 0.0006111,
        "low": 0.0006033,
        "close": 0.0006083
      },
      {
        "time": 1779377400,
        "open": 0.0006084,
        "high": 0.0006088,
        "low": 0.000603,
        "close": 0.0006048
      },
      {
        "time": 1779378300,
        "open": 0.0006049,
        "high": 0.0006068,
        "low": 0.0006031,
        "close": 0.0006041
      },
      {
        "time": 1779379200,
        "open": 0.0006042,
        "high": 0.0006064,
        "low": 0.0006001,
        "close": 0.0006017
      },
      {
        "time": 1779380100,
        "open": 0.0006018,
        "high": 0.000602,
        "low": 0.0005978,
        "close": 0.0005998
      },
      {
        "time": 1779381000,
        "open": 0.0005998,
        "high": 0.0006041,
        "low": 0.0005997,
        "close": 0.000601
      },
      {
        "time": 1779381900,
        "open": 0.000601,
        "high": 0.0006019,
        "low": 0.0005988,
        "close": 0.0006002
      },
      {
        "time": 1779382800,
        "open": 0.0006003,
        "high": 0.0006087,
        "low": 0.0005998,
        "close": 0.0006064
      },
      {
        "time": 1779383700,
        "open": 0.0006065,
        "high": 0.0006195,
        "low": 0.0006057,
        "close": 0.0006189
      },
      {
        "time": 1779384600,
        "open": 0.000619,
        "high": 0.00062,
        "low": 0.0006156,
        "close": 0.0006176
      },
      {
        "time": 1779385500,
        "open": 0.0006177,
        "high": 0.0006235,
        "low": 0.000616,
        "close": 0.0006195
      },
      {
        "time": 1779386400,
        "open": 0.0006195,
        "high": 0.0006207,
        "low": 0.0006153,
        "close": 0.0006165
      },
      {
        "time": 1779387300,
        "open": 0.0006166,
        "high": 0.0006212,
        "low": 0.0006154,
        "close": 0.0006169
      },
      {
        "time": 1779388200,
        "open": 0.0006169,
        "high": 0.0006172,
        "low": 0.0006141,
        "close": 0.0006159
      },
      {
        "time": 1779389100,
        "open": 0.0006159,
        "high": 0.0006163,
        "low": 0.0006066,
        "close": 0.000612
      },
      {
        "time": 1779390000,
        "open": 0.000612,
        "high": 0.0006142,
        "low": 0.0006105,
        "close": 0.0006137
      },
      {
        "time": 1779390900,
        "open": 0.0006137,
        "high": 0.0006148,
        "low": 0.0006115,
        "close": 0.000612
      },
      {
        "time": 1779391800,
        "open": 0.000612,
        "high": 0.0006141,
        "low": 0.0006117,
        "close": 0.0006129
      },
      {
        "time": 1779392700,
        "open": 0.0006128,
        "high": 0.000617,
        "low": 0.0006123,
        "close": 0.0006157
      },
      {
        "time": 1779393600,
        "open": 0.0006151,
        "high": 0.0006162,
        "low": 0.000614,
        "close": 0.0006144
      },
      {
        "time": 1779394500,
        "open": 0.0006145,
        "high": 0.0006147,
        "low": 0.0006123,
        "close": 0.0006131
      },
      {
        "time": 1779395400,
        "open": 0.0006131,
        "high": 0.0006146,
        "low": 0.0006128,
        "close": 0.0006146
      },
      {
        "time": 1779396300,
        "open": 0.0006149,
        "high": 0.0006165,
        "low": 0.0006118,
        "close": 0.0006126
      },
      {
        "time": 1779397200,
        "open": 0.0006127,
        "high": 0.0006153,
        "low": 0.0006127,
        "close": 0.0006142
      },
      {
        "time": 1779398100,
        "open": 0.0006142,
        "high": 0.0006173,
        "low": 0.0006142,
        "close": 0.0006171
      },
      {
        "time": 1779399000,
        "open": 0.0006172,
        "high": 0.0006178,
        "low": 0.0006146,
        "close": 0.000615
      },
      {
        "time": 1779399900,
        "open": 0.000615,
        "high": 0.0006157,
        "low": 0.000614,
        "close": 0.0006153
      },
      {
        "time": 1779400800,
        "open": 0.0006154,
        "high": 0.0006195,
        "low": 0.0006145,
        "close": 0.0006161
      },
      {
        "time": 1779401700,
        "open": 0.0006161,
        "high": 0.0006173,
        "low": 0.0006147,
        "close": 0.0006153
      },
      {
        "time": 1779402600,
        "open": 0.0006154,
        "high": 0.0006162,
        "low": 0.0006109,
        "close": 0.0006115
      },
      {
        "time": 1779403500,
        "open": 0.0006116,
        "high": 0.0006131,
        "low": 0.0006109,
        "close": 0.000612
      },
      {
        "time": 1779404400,
        "open": 0.0006119,
        "high": 0.0006138,
        "low": 0.0006098,
        "close": 0.0006098
      },
      {
        "time": 1779405300,
        "open": 0.0006097,
        "high": 0.0006115,
        "low": 0.0006087,
        "close": 0.0006109
      },
      {
        "time": 1779406200,
        "open": 0.0006108,
        "high": 0.000612,
        "low": 0.0006097,
        "close": 0.0006112
      }
    ]
  },
  "tradeId": "1779406448354-a5de3f"
}